[
  {
    "inputs": [
      {
        "internalType": "address",
        "name": "_controller",
        "type": "address"
      },
      {
        "internalType": "uint256",
        "name": "_epochLength",
        "type": "uint256"
      }
    ],
    "stateMutability": "nonpayable",
    "type": "constructor"
  },
  {
    "inputs": [],
    "name": "approveControllerChange",
    "outputs": [],
    "stateMutability": "nonpayable",
    "type": "function"
  },
  {
    "inputs": [
      {
        "internalType": "address",
        "name": "_user",
        "type": "address"
      },
      {
        "internalType": "uint256",
        "name": "epoch",
        "type": "uint256"
      }
    ],
    "name": "buyDistributionCredits",
    "outputs": [],
    "stateMutability": "payable",
    "type": "function"
  },
  {
    "inputs": [
      {
        "internalType": "address",
        "name": "_user",
        "type": "address"
      },
      {
        "internalType": "uint256",
        "name": "_epoch",
        "type": "uint256"
      }
    ],
    "name": "claimAbcReward",
    "outputs": [
      {
        "internalType": "uint256",
        "name": "amountClaimed",
        "type": "uint256"
      }
    ],
    "stateMutability": "nonpayable",
    "type": "function"
  },
  {
    "inputs": [],
    "name": "controller",
    "outputs": [
      {
        "internalType": "contract AbacusController",
        "name": "",
        "type": "address"
      }
    ],
    "stateMutability": "view",
    "type": "function"
  },
  {
    "inputs": [],
    "name": "currentEpoch",
    "outputs": [
      {
        "internalType": "uint256",
        "name": "",
        "type": "uint256"
      }
    ],
    "stateMutability": "view",
    "type": "function"
  },
  {
    "inputs": [],
    "name": "endEpoch",
    "outputs": [],
    "stateMutability": "nonpayable",
    "type": "function"
  },
  {
    "inputs": [
      {
        "internalType": "uint256",
        "name": "",
        "type": "uint256"
      }
    ],
    "name": "epochTracker",
    "outputs": [
      {
        "internalType": "uint256",
        "name": "totalCredits",
        "type": "uint256"
      },
      {
        "internalType": "uint256",
        "name": "startTime",
        "type": "uint256"
      },
      {
        "internalType": "uint256",
        "name": "abcEmissionSize",
        "type": "uint256"
      }
    ],
    "stateMutability": "view",
    "type": "function"
  },
  {
    "inputs": [],
    "name": "getCurrentAbcEmission",
    "outputs": [
      {
        "internalType": "uint256",
        "name": "",
        "type": "uint256"
      }
    ],
    "stateMutability": "view",
    "type": "function"
  },
  {
    "inputs": [],
    "name": "getCurrentEpoch",
    "outputs": [
      {
        "internalType": "uint256",
        "name": "epochNumber",
        "type": "uint256"
      }
    ],
    "stateMutability": "view",
    "type": "function"
  },
  {
    "inputs": [
      {
        "internalType": "uint256",
        "name": "_epoch",
        "type": "uint256"
      }
    ],
    "name": "getEpochEndTime",
    "outputs": [
      {
        "internalType": "uint256",
        "name": "endTime",
        "type": "uint256"
      }
    ],
    "stateMutability": "view",
    "type": "function"
  },
  {
    "inputs": [
      {
        "internalType": "uint256",
        "name": "_epoch",
        "type": "uint256"
      }
    ],
    "name": "getPastAbcEmission",
    "outputs": [
      {
        "internalType": "uint256",
        "name": "",
        "type": "uint256"
      }
    ],
    "stateMutability": "view",
    "type": "function"
  },
  {
    "inputs": [
      {
        "internalType": "uint256",
        "name": "_epoch",
        "type": "uint256"
      },
      {
        "internalType": "address",
        "name": "_user",
        "type": "address"
      }
    ],
    "name": "getUserCredits",
    "outputs": [
      {
        "internalType": "uint256",
        "name": "credits",
        "type": "uint256"
      }
    ],
    "stateMutability": "view",
    "type": "function"
  },
  {
    "inputs": [],
    "name": "pendingController",
    "outputs": [
      {
        "internalType": "address",
        "name": "",
        "type": "address"
      }
    ],
    "stateMutability": "view",
    "type": "function"
  },
  {
    "inputs": [
      {
        "internalType": "uint256",
        "name": "_amount",
        "type": "uint256"
      }
    ],
    "name": "receiveAbc",
    "outputs": [],
    "stateMutability": "nonpayable",
    "type": "function"
  },
  {
    "inputs": [
      {
        "internalType": "address",
        "name": "_controller",
        "type": "address"
      }
    ],
    "name": "setController",
    "outputs": [],
    "stateMutability": "nonpayable",
    "type": "function"
  },
  {
    "inputs": [
      {
        "internalType": "address",
        "name": "_nft",
        "type": "address"
      },
      {
        "internalType": "address",
        "name": "_user",
        "type": "address"
      },
      {
        "internalType": "uint256",
        "name": "_amount",
        "type": "uint256"
      }
    ],
    "name": "updateEpoch",
    "outputs": [],
    "stateMutability": "nonpayable",
    "type": "function"
  }
]